<annotation>
	<folder>img</folder>
	<filename>307.jpg</filename>
	<path>C:\Users\Administrator\Desktop\fall\img\307.jpg</path>
	<source>
		<database>Unknown</database>
	</source>
	<size>
		<width>852</width>
		<height>480</height>
		<depth>3</depth>
	</size>
	<segmented>0</segmented>
	<object>
		<name>nofall</name>
		<pose>Unspecified</pose>
		<truncated>0</truncated>
		<difficult>0</difficult>
		<bndbox>
			<xmin>453</xmin>
			<ymin>87</ymin>
			<xmax>536</xmax>
			<ymax>286</ymax>
		</bndbox>
	</object>
	<object>
		<name>nofall</name>
		<pose>Unspecified</pose>
		<truncated>0</truncated>
		<difficult>0</difficult>
		<bndbox>
			<xmin>536</xmin>
			<ymin>147</ymin>
			<xmax>637</xmax>
			<ymax>394</ymax>
		</bndbox>
	</object>
	<object>
		<name>nofall</name>
		<pose>Unspecified</pose>
		<truncated>0</truncated>
		<difficult>0</difficult>
		<bndbox>
			<xmin>724</xmin>
			<ymin>84</ymin>
			<xmax>776</xmax>
			<ymax>203</ymax>
		</bndbox>
	</object>
	<object>
		<name>nofall</name>
		<pose>Unspecified</pose>
		<truncated>0</truncated>
		<difficult>0</difficult>
		<bndbox>
			<xmin>774</xmin>
			<ymin>146</ymin>
			<xmax>823</xmax>
			<ymax>288</ymax>
		</bndbox>
	</object>
	<object>
		<name>nofall</name>
		<pose>Unspecified</pose>
		<truncated>0</truncated>
		<difficult>0</difficult>
		<bndbox>
			<xmin>546</xmin>
			<ymin>5</ymin>
			<xmax>595</xmax>
			<ymax>109</ymax>
		</bndbox>
	</object>
	<object>
		<name>nofall</name>
		<pose>Unspecified</pose>
		<truncated>0</truncated>
		<difficult>0</difficult>
		<bndbox>
			<xmin>87</xmin>
			<ymin>23</ymin>
			<xmax>173</xmax>
			<ymax>244</ymax>
		</bndbox>
	</object>
</annotation>
